burin/__init__.py
burin/_burin.py
burin/_config/__init__.py
burin/_config/basic_config.py
burin/_exceptions/__init__.py
burin/_filters/__init__.py
burin/_filters/filter.py
burin/_filters/filterer.py
burin/_formatters/__init__.py
burin/_formatters/_brace_style.py
burin/_formatters/_dollar_style.py
burin/_formatters/_percent_style.py
burin/_formatters/buffering_formatter.py
burin/_formatters/formatter.py
burin/_handlers/__init__.py
burin/_handlers/_references.py
burin/_handlers/_stderr_handler.py
burin/_handlers/base_rotating_handler.py
burin/_handlers/buffering_handler.py
burin/_handlers/datagram_handler.py
burin/_handlers/file_handler.py
burin/_handlers/handler.py
burin/_handlers/http_handler.py
burin/_handlers/memory_handler.py
burin/_handlers/nt_event_log_handler.py
burin/_handlers/null_handler.py
burin/_handlers/queue_handler.py
burin/_handlers/queue_listener.py
burin/_handlers/rotating_file_handler.py
burin/_handlers/smtp_handler.py
burin/_handlers/socket_handler.py
burin/_handlers/stream_handler.py
burin/_handlers/syslog_handler.py
burin/_handlers/timed_rotating_file_handler.py
burin/_handlers/watched_file_handler.py
burin/_log_levels/__init__.py
burin/_log_records/__init__.py
burin/_log_records/brace_record.py
burin/_log_records/dollar_record.py
burin/_log_records/log_record.py
burin/_log_records/percent_record.py
burin/_loggers/__init__.py
burin/_loggers/_manager.py
burin/_loggers/logger.py
burin/_loggers/logger_adapter.py
burin/_state/__init__.py
burin/_threading/__init__.py
burin/_threading/_fork_protection.py
burin/_threading/_lock.py
burin/_warnings/__init__.py
burin/_warnings/capture.py
burin-0.3.0.dist-info/METADATA
burin-0.3.0.dist-info/WHEEL
burin-0.3.0.dist-info/licenses/LICENSE
burin-0.3.0.dist-info/RECORD
