Metadata-Version: 2.3
Name: burin
Version: 0.3.0
Summary: Logging with added features and convenience.
Project-URL: Changelog, https://github.com/PeacefullyDisturbed/burin/blob/main/CHANGELOG.rst
Project-URL: Discussions, https://github.com/PeacefullyDisturbed/burin/discussions
Project-URL: Documentation, https://burin.readthedocs.io/
Project-URL: Issues, https://github.com/PeacefullyDisturbed/burin/issues
Project-URL: Source, https://github.com/PeacefullyDisturbed/burin
Author: William Foster
License-File: LICENSE
Keywords: logging
Classifier: Development Status :: 3 - Alpha
Classifier: Intended Audience :: Developers
Classifier: License :: OSI Approved :: BSD License
Classifier: Natural Language :: English
Classifier: Programming Language :: Python
Classifier: Programming Language :: Python :: 3 :: Only
Classifier: Programming Language :: Python :: 3.7
Classifier: Programming Language :: Python :: 3.8
Classifier: Programming Language :: Python :: 3.9
Classifier: Programming Language :: Python :: 3.10
Classifier: Programming Language :: Python :: 3.11
Classifier: Programming Language :: Python :: 3.12
Classifier: Topic :: Software Development :: Libraries
Requires-Python: >=3.7
Provides-Extra: dev
Requires-Dist: ruff~=0.4.8; extra == 'dev'
Provides-Extra: doc
Requires-Dist: sphinx-rtd-theme~=2.0.0; extra == 'doc'
Requires-Dist: sphinx~=7.3.7; extra == 'doc'
Provides-Extra: test
Requires-Dist: coverage[toml]~=7.2.7; (python_version == '3.7') and extra == 'test'
Requires-Dist: coverage[toml]~=7.5.3; (python_version >= '3.8' and python_version < '3.11') and extra == 'test'
Requires-Dist: coverage~=7.5.3; (python_version >= '3.11') and extra == 'test'
Requires-Dist: pytest~=7.4.4; (python_version == '3.7') and extra == 'test'
Requires-Dist: pytest~=8.2.2; (python_version >= '3.8') and extra == 'test'
